{
  "url": "https://www.inspiration.supply/",
  "requestedUrl": "https://www.inspiration.supply/",
  "timestamp": 1716652310679,
  "ranks": {
    "hundos": 106,
    "performance": 255,
    "accessibility": 31,
    "cumulative": 104
  },
  "lighthouse": {
    "version": "11.7.1",
    "performance": 0.97,
    "accessibility": 1,
    "bestPractices": 1,
    "seo": 1,
    "total": 397
  },
  "firstContentfulPaint": 1907.4095,
  "firstMeaningfulPaint": 1907.4095,
  "speedIndex": 1947.3025929992973,
  "largestContentfulPaint": 2149.5275,
  "totalBlockingTime": 0,
  "cumulativeLayoutShift": 0,
  "timeToInteractive": 1907.4095,
  "maxPotentialFirstInputDelay": 16,
  "timeToFirstByte": 120.07900000000001,
  "weight": {
    "summary": "14 requests • 158.7 KiB",
    "total": 162487,
    "image": 136847,
    "imageCount": 6,
    "script": 13848,
    "scriptCount": 3,
    "document": 4004,
    "font": 0,
    "fontCount": 0,
    "stylesheet": 6639,
    "stylesheetCount": 1,
    "thirdParty": 9827,
    "thirdPartyCount": 3
  },
  "run": {
    "number": 2,
    "total": 3
  },
  "sidequests": {
    "-weight.total": 139,
    "+weight.total": 595,
    "-weight.document": 79,
    "+weight.document": 644,
    "-weight.script": 146,
    "+weight.script": 525,
    "-weight.image": 246,
    "+weight.image": 414,
    "-weight.font": 1,
    "+weight.font": 563,
    "+weight.fontCount": 18,
    "-timeToFirstByte": 375,
    "-totalBlockingTime": 1,
    "-largestContentfulPaint": 317
  },
  "axe": {
    "passes": 474,
    "violations": 0
  }
}