{
  "url": "https://www.fastlink.lt/lt/",
  "requestedUrl": "https://www.fastlink.lt/lt/",
  "timestamp": 1701617094511,
  "ranks": {
    "hundos": 500,
    "performance": 516,
    "accessibility": 454,
    "cumulative": 500
  },
  "lighthouse": {
    "version": "9.6.8",
    "performance": 0.27,
    "accessibility": 0.81,
    "bestPractices": 1,
    "seo": 0.97,
    "total": 305
  },
  "firstContentfulPaint": 4344.04,
  "firstMeaningfulPaint": 4944.04,
  "speedIndex": 5642.692858515138,
  "largestContentfulPaint": 9401.205999999998,
  "totalBlockingTime": 1097.000000000001,
  "cumulativeLayoutShift": 0.16956286833021372,
  "timeToInteractive": 10260.571,
  "maxPotentialFirstInputDelay": 334,
  "timeToFirstByte": 151.43699999999995,
  "weight": {
    "summary": "75 requests • 1,384 KiB",
    "total": 1416787,
    "image": 478210,
    "imageCount": 31,
    "script": 718135,
    "scriptCount": 23,
    "document": 103513,
    "font": 59868,
    "fontCount": 6,
    "stylesheet": 36641,
    "stylesheetCount": 5,
    "thirdParty": 782759,
    "thirdPartyCount": 33
  },
  "run": {
    "number": 1,
    "total": 3
  },
  "sidequests": {
    "-weight.total": 383,
    "+weight.total": 144,
    "-weight.document": 501,
    "+weight.document": 23,
    "-weight.script": 451,
    "+weight.script": 36,
    "-weight.image": 317,
    "+weight.image": 156,
    "-weight.font": 181,
    "+weight.font": 221,
    "+weight.fontCount": 12,
    "-timeToFirstByte": 405,
    "-totalBlockingTime": 307,
    "-largestContentfulPaint": 506
  },
  "axe": {
    "passes": 1730,
    "violations": 58
  }
}