{
  "url": "https://nomorenoisegame.com/",
  "requestedUrl": "https://nomorenoisegame.com/",
  "timestamp": 1690878314928,
  "ranks": {
    "hundos": 383,
    "performance": 400,
    "accessibility": 240,
    "cumulative": 381
  },
  "lighthouse": {
    "version": "9.6.8",
    "performance": 0.36,
    "accessibility": 0.94,
    "bestPractices": 0.92,
    "seo": 1,
    "total": 322
  },
  "firstContentfulPaint": 3713.9245,
  "firstMeaningfulPaint": 3713.9245,
  "speedIndex": 8470.658179978762,
  "largestContentfulPaint": 15381.243999999997,
  "totalBlockingTime": 552.5,
  "cumulativeLayoutShift": 0,
  "timeToInteractive": 14755.558999999997,
  "maxPotentialFirstInputDelay": 392,
  "timeToFirstByte": 85.71699999999998,
  "weight": {
    "summary": "45 requests • 9,373 KiB",
    "total": 9597662,
    "image": 8166255,
    "imageCount": 16,
    "script": 921320,
    "scriptCount": 6,
    "document": 39659,
    "font": 290917,
    "fontCount": 6,
    "stylesheet": 147471,
    "stylesheetCount": 9,
    "thirdParty": 1449070,
    "thirdPartyCount": 31
  },
  "run": {
    "number": 2,
    "total": 3
  },
  "sidequests": {
    "-weight.total": 402,
    "+weight.total": 10,
    "-weight.document": 350,
    "+weight.document": 57,
    "-weight.script": 356,
    "+weight.script": 18,
    "-weight.image": 361,
    "+weight.image": 6,
    "-weight.font": 279,
    "+weight.font": 33,
    "+weight.fontCount": 12,
    "-timeToFirstByte": 258,
    "-totalBlockingTime": 193,
    "-largestContentfulPaint": 407
  },
  "axe": {
    "passes": 276,
    "violations": 5
  }
}