{
  "url": "https://openmoji.org/",
  "requestedUrl": "https://openmoji.org/",
  "timestamp": 1682962397359,
  "ranks": {
    "hundos": 260,
    "performance": 252,
    "accessibility": 242,
    "cumulative": 261
  },
  "lighthouse": {
    "version": "9.6.8",
    "performance": 0.72,
    "accessibility": 0.84,
    "bestPractices": 0.92,
    "seo": 0.83,
    "total": 331
  },
  "firstContentfulPaint": 2748.985,
  "firstMeaningfulPaint": 3795.2385,
  "speedIndex": 4907.550339752344,
  "largestContentfulPaint": 3638.695,
  "totalBlockingTime": 290.5,
  "cumulativeLayoutShift": 0.00476266818576389,
  "timeToInteractive": 7026.052,
  "maxPotentialFirstInputDelay": 329,
  "timeToFirstByte": 199.06500000000005,
  "weight": {
    "summary": "335 requests • 1,506 KiB",
    "total": 1542642,
    "image": 951301,
    "imageCount": 314,
    "script": 352196,
    "scriptCount": 10,
    "document": 27215,
    "font": 39927,
    "fontCount": 3,
    "stylesheet": 49553,
    "stylesheetCount": 3,
    "thirdParty": 258199,
    "thirdPartyCount": 8
  },
  "run": {
    "number": 3,
    "total": 3
  },
  "sidequests": {
    "-weight.total": 230,
    "+weight.total": 57,
    "-weight.document": 238,
    "+weight.document": 48,
    "-weight.script": 218,
    "+weight.script": 33,
    "-weight.image": 209,
    "+weight.image": 46,
    "-weight.font": 64,
    "+weight.font": 149,
    "+weight.fontCount": 13,
    "-timeToFirstByte": 226,
    "-totalBlockingTime": 115,
    "-largestContentfulPaint": 237
  },
  "axe": {
    "passes": 1895,
    "violations": 301
  }
}