{
  "url": "https://okikio.dev/",
  "requestedUrl": "https://okikio.dev/",
  "timestamp": 1716657885160,
  "ranks": {
    "hundos": 108,
    "performance": 266,
    "accessibility": 135,
    "cumulative": 109
  },
  "lighthouse": {
    "version": "11.7.1",
    "performance": 0.97,
    "accessibility": 1,
    "bestPractices": 1,
    "seo": 1,
    "total": 397
  },
  "firstContentfulPaint": 1122.1495,
  "firstMeaningfulPaint": 1122.1495,
  "speedIndex": 2667.0399726013643,
  "largestContentfulPaint": 2518.6175,
  "totalBlockingTime": 35,
  "cumulativeLayoutShift": 0,
  "timeToInteractive": 2097.1495,
  "maxPotentialFirstInputDelay": 120,
  "timeToFirstByte": 159.546,
  "weight": {
    "summary": "13 requests • 162.8 KiB",
    "total": 166727,
    "image": 67034,
    "imageCount": 1,
    "script": 10135,
    "scriptCount": 3,
    "document": 11429,
    "font": 62230,
    "fontCount": 2,
    "stylesheet": 14575,
    "stylesheetCount": 2,
    "thirdParty": 68358,
    "thirdPartyCount": 2
  },
  "run": {
    "number": 3,
    "total": 3
  },
  "sidequests": {
    "-weight.total": 145,
    "+weight.total": 589,
    "-weight.document": 393,
    "+weight.document": 330,
    "-weight.script": 117,
    "+weight.script": 554,
    "-weight.image": 182,
    "+weight.image": 478,
    "-weight.font": 250,
    "+weight.font": 313,
    "+weight.fontCount": 16,
    "-timeToFirstByte": 496,
    "-totalBlockingTime": 62,
    "-largestContentfulPaint": 376
  },
  "axe": {
    "passes": 615,
    "violations": 1
  }
}