{
  "url": "https://www.miduconf.com/",
  "requestedUrl": "https://miduconf.com/",
  "timestamp": 1716546397319,
  "ranks": {
    "hundos": 501,
    "performance": 598,
    "accessibility": 407,
    "cumulative": 499
  },
  "lighthouse": {
    "version": "9.6.8",
    "performance": 0.62,
    "accessibility": 0.96,
    "bestPractices": 1,
    "seo": 1,
    "total": 358
  },
  "firstContentfulPaint": 2657.3,
  "firstMeaningfulPaint": 2657.3,
  "speedIndex": 7606.703958482034,
  "largestContentfulPaint": 3908.3,
  "totalBlockingTime": 505.5,
  "cumulativeLayoutShift": 0.000024361080593532986,
  "timeToInteractive": 4619.690949249268,
  "maxPotentialFirstInputDelay": 700,
  "timeToFirstByte": 2178.496,
  "weight": {
    "summary": "36 requests • 404 KiB",
    "total": 413714,
    "image": 282003,
    "imageCount": 12,
    "script": 11183,
    "scriptCount": 17,
    "document": 21624,
    "font": 84006,
    "fontCount": 2,
    "stylesheet": 13686,
    "stylesheetCount": 2,
    "thirdParty": 0,
    "thirdPartyCount": 0
  },
  "run": {
    "number": 1,
    "total": 3
  },
  "sidequests": {
    "-weight.total": 312,
    "+weight.total": 426,
    "-weight.document": 554,
    "+weight.document": 178,
    "-weight.script": 131,
    "+weight.script": 547,
    "-weight.image": 357,
    "+weight.image": 307,
    "-weight.font": 324,
    "+weight.font": 229,
    "+weight.fontCount": 17,
    "-timeToFirstByte": 724,
    "-totalBlockingTime": 329,
    "-largestContentfulPaint": 608
  },
  "axe": {
    "passes": 873,
    "violations": 15
  }
}