{
  "url": "https://jjaimealeman.com/",
  "requestedUrl": "https://jjaimealeman.com/",
  "timestamp": 1728933714252,
  "ranks": {
    "hundos": 167,
    "performance": 127,
    "accessibility": 444,
    "cumulative": 166
  },
  "lighthouse": {
    "version": "11.7.1",
    "performance": 1,
    "accessibility": 0.95,
    "bestPractices": 1,
    "seo": 1,
    "total": 395
  },
  "firstContentfulPaint": 1301.192,
  "firstMeaningfulPaint": 1425.3955,
  "speedIndex": 1491.7954234503827,
  "largestContentfulPaint": 1790.256,
  "totalBlockingTime": 0,
  "cumulativeLayoutShift": 0,
  "timeToInteractive": 1425.3955,
  "maxPotentialFirstInputDelay": 31,
  "timeToFirstByte": 148.626,
  "weight": {
    "summary": "10 requests • 76.5 KiB",
    "total": 78320,
    "image": 9977,
    "imageCount": 2,
    "script": 12783,
    "scriptCount": 2,
    "document": 14731,
    "font": 31689,
    "fontCount": 2,
    "stylesheet": 8543,
    "stylesheetCount": 1,
    "thirdParty": 7096,
    "thirdPartyCount": 1
  },
  "run": {
    "number": 3,
    "total": 3
  },
  "sidequests": {
    "-weight.total": 101,
    "+weight.total": 924,
    "-weight.document": 650,
    "+weight.document": 362,
    "-weight.script": 185,
    "+weight.script": 776,
    "-weight.image": 82,
    "+weight.image": 832,
    "-weight.font": 110,
    "+weight.font": 634,
    "+weight.fontCount": 17,
    "-timeToFirstByte": 734,
    "-totalBlockingTime": 1,
    "-largestContentfulPaint": 214
  },
  "axe": {
    "passes": 224,
    "violations": 3
  }
}