{
  "url": "https://yogendrakumarvr.com/",
  "requestedUrl": "https://yogendrakumarvr.com/",
  "timestamp": 1716580054910,
  "ranks": {
    "hundos": 524,
    "performance": 571,
    "accessibility": 363,
    "cumulative": 527
  },
  "lighthouse": {
    "version": "9.6.8",
    "performance": 0.65,
    "accessibility": 0.97,
    "bestPractices": 0.92,
    "seo": 1,
    "total": 354
  },
  "firstContentfulPaint": 1688.663,
  "firstMeaningfulPaint": 1688.663,
  "speedIndex": 2972.4486190066004,
  "largestContentfulPaint": 6931.350999999999,
  "totalBlockingTime": 59.217500000000086,
  "cumulativeLayoutShift": 0.35250360404120556,
  "timeToInteractive": 1823.6839999999997,
  "maxPotentialFirstInputDelay": 139,
  "timeToFirstByte": 1031.685,
  "weight": {
    "summary": "22 requests • 1,462 KiB",
    "total": 1497276,
    "image": 1384617,
    "imageCount": 5,
    "script": 60000,
    "scriptCount": 9,
    "document": 5081,
    "font": 39923,
    "fontCount": 2,
    "stylesheet": 7456,
    "stylesheetCount": 4,
    "thirdParty": 1426170,
    "thirdPartyCount": 9
  },
  "run": {
    "number": 3,
    "total": 3
  },
  "sidequests": {
    "-weight.total": 539,
    "+weight.total": 199,
    "-weight.document": 141,
    "+weight.document": 591,
    "-weight.script": 273,
    "+weight.script": 405,
    "-weight.image": 545,
    "+weight.image": 119,
    "-weight.font": 150,
    "+weight.font": 403,
    "+weight.fontCount": 17,
    "-timeToFirstByte": 700,
    "-totalBlockingTime": 78,
    "-largestContentfulPaint": 377
  },
  "axe": {
    "passes": 105,
    "violations": 14
  }
}