{
  "url": "https://jacobsonlawrence.com/",
  "requestedUrl": "https://www.jacobsonlawrence.com/",
  "timestamp": 1710355560527,
  "ranks": {
    "hundos": 297,
    "performance": 267,
    "accessibility": 216,
    "cumulative": 297
  },
  "lighthouse": {
    "version": "9.6.8",
    "performance": 0.93,
    "accessibility": 1,
    "bestPractices": 0.83,
    "seo": 1,
    "total": 376
  },
  "firstContentfulPaint": 1859.097,
  "firstMeaningfulPaint": 1907.097,
  "speedIndex": 2098.2726560864453,
  "largestContentfulPaint": 2153.0969999999998,
  "totalBlockingTime": 222.99999999999977,
  "cumulativeLayoutShift": 0.0038230779435899525,
  "timeToInteractive": 3610.5969999999998,
  "maxPotentialFirstInputDelay": 174.99999999999977,
  "timeToFirstByte": 39.288,
  "weight": {
    "summary": "11 requests • 578 KiB",
    "total": 592173,
    "image": 512591,
    "imageCount": 5,
    "script": 4797,
    "scriptCount": 1,
    "document": 16424,
    "font": 46914,
    "fontCount": 1,
    "stylesheet": 11126,
    "stylesheetCount": 1,
    "thirdParty": 0,
    "thirdPartyCount": 0
  },
  "run": {
    "number": 3,
    "total": 3
  },
  "sidequests": {
    "-weight.total": 366,
    "+weight.total": 304,
    "-weight.document": 457,
    "+weight.document": 204,
    "-weight.script": 73,
    "+weight.script": 542,
    "-weight.image": 404,
    "+weight.image": 196,
    "-weight.font": 183,
    "+weight.font": 334,
    "+weight.fontCount": 19,
    "-timeToFirstByte": 180,
    "-totalBlockingTime": 198,
    "-largestContentfulPaint": 227
  },
  "axe": {
    "passes": 439,
    "violations": 26
  }
}