{
  "url": "https://divriots.com/",
  "requestedUrl": "https://divriots.com/",
  "timestamp": 1714833945465,
  "ranks": {
    "hundos": 289,
    "performance": 280,
    "accessibility": 361,
    "cumulative": 286
  },
  "lighthouse": {
    "version": "9.6.8",
    "performance": 0.75,
    "accessibility": 0.96,
    "bestPractices": 0.92,
    "seo": 1,
    "total": 363
  },
  "firstContentfulPaint": 1145.426,
  "firstMeaningfulPaint": 1145.426,
  "speedIndex": 1477.7211197330107,
  "largestContentfulPaint": 2339.426,
  "totalBlockingTime": 1057.5,
  "cumulativeLayoutShift": 0.006530995368957519,
  "timeToInteractive": 3423.926,
  "maxPotentialFirstInputDelay": 135,
  "timeToFirstByte": 89.42600000000002,
  "weight": {
    "summary": "20 requests • 169 KiB",
    "total": 172887,
    "image": 34865,
    "imageCount": 8,
    "script": 5779,
    "scriptCount": 4,
    "document": 7144,
    "font": 106233,
    "fontCount": 2,
    "stylesheet": 18866,
    "stylesheetCount": 5,
    "thirdParty": 18221,
    "thirdPartyCount": 3
  },
  "run": {
    "number": 2,
    "total": 3
  },
  "sidequests": {
    "-weight.total": 160,
    "+weight.total": 555,
    "-weight.document": 245,
    "+weight.document": 465,
    "-weight.script": 82,
    "+weight.script": 576,
    "-weight.image": 127,
    "+weight.image": 516,
    "-weight.font": 359,
    "+weight.font": 185,
    "+weight.fontCount": 17,
    "-timeToFirstByte": 387,
    "-totalBlockingTime": 285,
    "-largestContentfulPaint": 461
  },
  "axe": {
    "passes": 624,
    "violations": 2
  }
}