{
  "url": "https://www.levelshuddersfield.co.uk/",
  "requestedUrl": "https://www.levelshuddersfield.co.uk/",
  "timestamp": 1705688323579,
  "ranks": {
    "hundos": 586,
    "performance": 592,
    "accessibility": 412,
    "cumulative": 586
  },
  "lighthouse": {
    "version": "9.6.8",
    "performance": null,
    "accessibility": 0.91,
    "bestPractices": 1,
    "seo": 0.92,
    "total": 283
  },
  "firstContentfulPaint": 2056.845,
  "firstMeaningfulPaint": 2108.845,
  "speedIndex": 2706.715912570681,
  "totalBlockingTime": 387.29399999999987,
  "cumulativeLayoutShift": 0,
  "timeToInteractive": 4717.883,
  "maxPotentialFirstInputDelay": 371,
  "timeToFirstByte": 331.3109999999999,
  "weight": {
    "summary": "18 requests • 521 KiB",
    "total": 533556,
    "image": 228036,
    "imageCount": 5,
    "script": 213475,
    "scriptCount": 6,
    "document": 12721,
    "font": 53708,
    "fontCount": 3,
    "stylesheet": 25352,
    "stylesheetCount": 1,
    "thirdParty": 197833,
    "thirdPartyCount": 5
  },
  "sidequests": {
    "-weight.total": 327,
    "+weight.total": 267,
    "-weight.document": 359,
    "+weight.document": 226,
    "-weight.script": 402,
    "+weight.script": 142,
    "-weight.image": 264,
    "+weight.image": 266,
    "-weight.font": 195,
    "+weight.font": 254,
    "+weight.fontCount": 15,
    "-timeToFirstByte": 464,
    "-totalBlockingTime": 241,
    "-largestContentfulPaint": 312
  },
  "axe": {
    "passes": 956,
    "violations": 19
  }
}