{
  "url": "https://www.ianwootten.co.uk/",
  "requestedUrl": "https://www.ianwootten.co.uk/",
  "timestamp": 1714835795611,
  "ranks": {
    "hundos": 87,
    "performance": 170,
    "accessibility": 33,
    "cumulative": 85
  },
  "lighthouse": {
    "version": "9.6.8",
    "performance": 0.91,
    "accessibility": 1,
    "bestPractices": 1,
    "seo": 1,
    "total": 391
  },
  "firstContentfulPaint": 1058.5420000000001,
  "firstMeaningfulPaint": 1121.0420000000001,
  "speedIndex": 1588.4977582884044,
  "largestContentfulPaint": 1683.694,
  "totalBlockingTime": 364.5,
  "cumulativeLayoutShift": 0.0021677398681640625,
  "timeToInteractive": 2449.7715,
  "maxPotentialFirstInputDelay": 223,
  "timeToFirstByte": 77.68300000000002,
  "weight": {
    "summary": "24 requests • 554 KiB",
    "total": 567654,
    "image": 148194,
    "imageCount": 8,
    "script": 360202,
    "scriptCount": 2,
    "document": 7836,
    "font": 38277,
    "fontCount": 1,
    "stylesheet": 10630,
    "stylesheetCount": 3,
    "thirdParty": 436871,
    "thirdPartyCount": 6
  },
  "run": {
    "number": 2,
    "total": 3
  },
  "sidequests": {
    "-weight.total": 379,
    "+weight.total": 336,
    "-weight.document": 283,
    "+weight.document": 427,
    "-weight.script": 540,
    "+weight.script": 118,
    "-weight.image": 257,
    "+weight.image": 386,
    "-weight.font": 139,
    "+weight.font": 405,
    "+weight.fontCount": 18,
    "-timeToFirstByte": 323,
    "-totalBlockingTime": 168,
    "-largestContentfulPaint": 108
  },
  "axe": {
    "passes": 306,
    "violations": 0
  }
}