{
  "url": "https://mesaschool.co/",
  "requestedUrl": "https://mesaschool.co/",
  "timestamp": 1708026739714,
  "ranks": {
    "hundos": 624,
    "performance": 622,
    "accessibility": 511,
    "cumulative": 625
  },
  "lighthouse": {
    "version": "9.6.8",
    "performance": 0.28,
    "accessibility": 0.86,
    "bestPractices": 0.75,
    "seo": 1,
    "total": 289
  },
  "firstContentfulPaint": 2769.449,
  "firstMeaningfulPaint": 4229.109,
  "speedIndex": 5650.827933807326,
  "largestContentfulPaint": 6336.73,
  "totalBlockingTime": 2962.403000000001,
  "cumulativeLayoutShift": 0.17493408203125002,
  "timeToInteractive": 9168.575,
  "maxPotentialFirstInputDelay": 770.0000000000009,
  "timeToFirstByte": 439.48199999999997,
  "weight": {
    "summary": "148 requests • 12,301 KiB",
    "total": 12596724,
    "image": 11884090,
    "imageCount": 104,
    "script": 522375,
    "scriptCount": 18,
    "document": 15494,
    "font": 111838,
    "fontCount": 5,
    "stylesheet": 57686,
    "stylesheetCount": 7,
    "thirdParty": 475277,
    "thirdPartyCount": 40
  },
  "run": {
    "number": 3,
    "total": 3
  },
  "sidequests": {
    "-weight.total": 627,
    "+weight.total": 12,
    "-weight.document": 420,
    "+weight.document": 209,
    "-weight.script": 540,
    "+weight.script": 49,
    "-weight.image": 564,
    "+weight.image": 11,
    "-weight.font": 334,
    "+weight.font": 152,
    "+weight.fontCount": 14,
    "-timeToFirstByte": 571,
    "-totalBlockingTime": 452,
    "-largestContentfulPaint": 600
  },
  "axe": {
    "passes": 1395,
    "violations": 104
  }
}