{
  "url": "https://simloud.com/",
  "requestedUrl": "https://simloud.com/",
  "timestamp": 1716575616476,
  "ranks": {
    "hundos": 633,
    "performance": 609,
    "accessibility": 619,
    "cumulative": 634
  },
  "lighthouse": {
    "version": "9.6.8",
    "performance": 0.59,
    "accessibility": 0.85,
    "bestPractices": 0.92,
    "seo": 0.92,
    "total": 328
  },
  "firstContentfulPaint": 2664.0745,
  "firstMeaningfulPaint": 2664.0745,
  "speedIndex": 2728.90798876552,
  "largestContentfulPaint": 7522.330000000002,
  "totalBlockingTime": 386.34849999999983,
  "cumulativeLayoutShift": 0,
  "timeToInteractive": 5534.119499999999,
  "maxPotentialFirstInputDelay": 173,
  "timeToFirstByte": 15.767000000000024,
  "weight": {
    "summary": "76 requests • 2,997 KiB",
    "total": 3069376,
    "image": 1131408,
    "imageCount": 52,
    "script": 234745,
    "scriptCount": 14,
    "document": 101131,
    "font": 46656,
    "fontCount": 1,
    "stylesheet": 15220,
    "stylesheetCount": 1,
    "thirdParty": 525489,
    "thirdPartyCount": 31
  },
  "run": {
    "number": 3,
    "total": 3
  },
  "sidequests": {
    "-weight.total": 638,
    "+weight.total": 100,
    "-weight.document": 701,
    "+weight.document": 31,
    "-weight.script": 482,
    "+weight.script": 196,
    "-weight.image": 526,
    "+weight.image": 138,
    "-weight.font": 180,
    "+weight.font": 373,
    "+weight.fontCount": 18,
    "-timeToFirstByte": 29,
    "-totalBlockingTime": 292,
    "-largestContentfulPaint": 696
  },
  "axe": {
    "passes": 1793,
    "violations": 101
  }
}