{
  "url": "https://www.sayics.com/",
  "requestedUrl": "https://www.sayics.com/",
  "timestamp": 1716553036769,
  "ranks": {
    "hundos": 279,
    "performance": 285,
    "accessibility": 401,
    "cumulative": 282
  },
  "lighthouse": {
    "version": "9.6.8",
    "performance": 0.94,
    "accessibility": 0.96,
    "bestPractices": 0.92,
    "seo": 1,
    "total": 382
  },
  "firstContentfulPaint": 1942.5559999999998,
  "firstMeaningfulPaint": 2180.393,
  "speedIndex": 2233.2824844654942,
  "largestContentfulPaint": 2418.23,
  "totalBlockingTime": 76.99999999999977,
  "cumulativeLayoutShift": 0.0011472066243489584,
  "timeToInteractive": 4691.7185,
  "maxPotentialFirstInputDelay": 121,
  "timeToFirstByte": 41.554,
  "weight": {
    "summary": "49 requests • 2,610 KiB",
    "total": 2672999,
    "image": 86908,
    "imageCount": 12,
    "script": 235234,
    "scriptCount": 26,
    "document": 10261,
    "font": 77381,
    "fontCount": 3,
    "stylesheet": 26024,
    "stylesheetCount": 3,
    "thirdParty": 2421375,
    "thirdPartyCount": 11
  },
  "run": {
    "number": 1,
    "total": 3
  },
  "sidequests": {
    "-weight.total": 621,
    "+weight.total": 117,
    "-weight.document": 363,
    "+weight.document": 369,
    "-weight.script": 483,
    "+weight.script": 195,
    "-weight.image": 209,
    "+weight.image": 455,
    "-weight.font": 300,
    "+weight.font": 253,
    "+weight.fontCount": 16,
    "-timeToFirstByte": 222,
    "-totalBlockingTime": 94,
    "-largestContentfulPaint": 269
  },
  "axe": {
    "passes": 605,
    "violations": 8
  }
}