{
  "url": "https://www.davidtapias.com/",
  "requestedUrl": "https://www.davidtapias.com/",
  "timestamp": 1727807603798,
  "ranks": {
    "hundos": 393,
    "performance": 147,
    "accessibility": 694,
    "cumulative": 390
  },
  "lighthouse": {
    "version": "11.7.1",
    "performance": 1,
    "accessibility": 0.9,
    "bestPractices": 1,
    "seo": 0.92,
    "total": 382
  },
  "firstContentfulPaint": 1193.2765,
  "firstMeaningfulPaint": 1193.2765,
  "speedIndex": 1877.6399371909972,
  "largestContentfulPaint": 1524.2765,
  "totalBlockingTime": 34.5,
  "cumulativeLayoutShift": 0.00024258173742903075,
  "timeToInteractive": 2468.2765,
  "maxPotentialFirstInputDelay": 119,
  "timeToFirstByte": 23.489000000000004,
  "weight": {
    "summary": "6 requests • 375.8 KiB",
    "total": 384860,
    "image": 75453,
    "imageCount": 1,
    "script": 5055,
    "scriptCount": 1,
    "document": 1766,
    "font": 275892,
    "fontCount": 2,
    "stylesheet": 26694,
    "stylesheetCount": 1,
    "thirdParty": 0,
    "thirdPartyCount": 0
  },
  "run": {
    "number": 1,
    "total": 3
  },
  "sidequests": {
    "-weight.total": 405,
    "+weight.total": 618,
    "-weight.document": 17,
    "+weight.document": 981,
    "-weight.script": 94,
    "+weight.script": 863,
    "-weight.image": 268,
    "+weight.image": 642,
    "-weight.font": 637,
    "+weight.font": 106,
    "+weight.fontCount": 17,
    "-timeToFirstByte": 227,
    "-totalBlockingTime": 67,
    "-largestContentfulPaint": 138
  },
  "axe": {
    "passes": 70,
    "violations": 2
  }
}