{
  "url": "https://stefenphelps.com/",
  "requestedUrl": "https://stefenphelps.com/",
  "timestamp": 1696395791275,
  "ranks": {
    "hundos": 28,
    "performance": 35,
    "accessibility": 52,
    "cumulative": 21
  },
  "lighthouse": {
    "version": "9.6.8",
    "performance": 1,
    "accessibility": 1,
    "bestPractices": 1,
    "seo": 1,
    "total": 400
  },
  "firstContentfulPaint": 1067.306,
  "firstMeaningfulPaint": 1067.306,
  "speedIndex": 1067.306,
  "largestContentfulPaint": 1134.306,
  "totalBlockingTime": 0,
  "cumulativeLayoutShift": 0,
  "timeToInteractive": 1067.306,
  "maxPotentialFirstInputDelay": 16,
  "timeToFirstByte": 26.312999999999988,
  "weight": {
    "summary": "13 requests • 51 KiB",
    "total": 52614,
    "image": 5173,
    "imageCount": 2,
    "script": 4283,
    "scriptCount": 3,
    "document": 5746,
    "font": 15329,
    "fontCount": 1,
    "stylesheet": 2496,
    "stylesheetCount": 1,
    "thirdParty": 0,
    "thirdPartyCount": 0
  },
  "run": {
    "number": 3,
    "total": 3
  },
  "sidequests": {
    "-weight.total": 33,
    "+weight.total": 439,
    "-weight.document": 151,
    "+weight.document": 318,
    "-weight.script": 58,
    "+weight.script": 373,
    "-weight.image": 24,
    "+weight.image": 396,
    "-weight.font": 15,
    "+weight.font": 336,
    "+weight.fontCount": 18,
    "-timeToFirstByte": 208,
    "-totalBlockingTime": 1,
    "-largestContentfulPaint": 36
  },
  "axe": {
    "passes": 152,
    "violations": 0
  }
}