{
  "url": "https://dtxautosalon.com/",
  "requestedUrl": "https://dtxautosalon.com/",
  "timestamp": 1726577203091,
  "ranks": {
    "hundos": 548,
    "performance": 620,
    "accessibility": 725,
    "cumulative": 547
  },
  "lighthouse": {
    "version": "11.7.1",
    "performance": 0.79,
    "accessibility": 0.89,
    "bestPractices": 1,
    "seo": 1,
    "total": 368
  },
  "firstContentfulPaint": 1854.4054999999998,
  "firstMeaningfulPaint": 1854.4054999999998,
  "speedIndex": 2873.638068328787,
  "largestContentfulPaint": 3742.7664999999997,
  "totalBlockingTime": 333,
  "cumulativeLayoutShift": 0.07840352411091843,
  "timeToInteractive": 6730.5735,
  "maxPotentialFirstInputDelay": 299,
  "timeToFirstByte": 150.38899999999998,
  "weight": {
    "summary": "34 requests • 3.0 MiB",
    "total": 3140424,
    "image": 2714776,
    "imageCount": 15,
    "script": 177632,
    "scriptCount": 9,
    "document": 10104,
    "font": 210325,
    "fontCount": 5,
    "stylesheet": 27342,
    "stylesheetCount": 3,
    "thirdParty": 467975,
    "thirdPartyCount": 5
  },
  "run": {
    "number": 1,
    "total": 3
  },
  "sidequests": {
    "-weight.total": 855,
    "+weight.total": 132,
    "-weight.document": 473,
    "+weight.document": 495,
    "-weight.script": 603,
    "+weight.script": 318,
    "-weight.image": 797,
    "+weight.image": 81,
    "-weight.font": 584,
    "+weight.font": 132,
    "+weight.fontCount": 15,
    "-timeToFirstByte": 691,
    "-totalBlockingTime": 326,
    "-largestContentfulPaint": 792
  },
  "axe": {
    "passes": 384,
    "violations": 14
  }
}