{
  "url": "https://tubog-showcase.ru/",
  "requestedUrl": "https://tubog-showcase.ru/",
  "timestamp": 1726584151525,
  "ranks": {
    "hundos": 254,
    "performance": 293,
    "accessibility": 578,
    "cumulative": 247
  },
  "lighthouse": {
    "version": "11.7.1",
    "performance": 0.98,
    "accessibility": 0.93,
    "bestPractices": 1,
    "seo": 1,
    "total": 391
  },
  "firstContentfulPaint": 1686.1260000000002,
  "firstMeaningfulPaint": 1686.1260000000002,
  "speedIndex": 3225.208931999696,
  "largestContentfulPaint": 1761.5710000000001,
  "totalBlockingTime": 0,
  "cumulativeLayoutShift": 0,
  "timeToInteractive": 1686.1260000000002,
  "maxPotentialFirstInputDelay": 16,
  "timeToFirstByte": 1174.513,
  "weight": {
    "summary": "13 requests • 176.9 KiB",
    "total": 181116,
    "image": 141958,
    "imageCount": 7,
    "script": 26044,
    "scriptCount": 3,
    "document": 8652,
    "font": 0,
    "fontCount": 0,
    "stylesheet": 4089,
    "stylesheetCount": 1,
    "thirdParty": 20857,
    "thirdPartyCount": 1
  },
  "run": {
    "number": 1,
    "total": 3
  },
  "sidequests": {
    "-weight.total": 232,
    "+weight.total": 755,
    "-weight.document": 399,
    "+weight.document": 569,
    "-weight.script": 272,
    "+weight.script": 649,
    "-weight.image": 347,
    "+weight.image": 531,
    "-weight.font": 1,
    "+weight.font": 716,
    "+weight.fontCount": 20,
    "-timeToFirstByte": 941,
    "-totalBlockingTime": 1,
    "-largestContentfulPaint": 606
  },
  "axe": {
    "passes": 256,
    "violations": 6
  }
}