{
  "url": "https://crosstownmovers.net/",
  "requestedUrl": "https://crosstownmovers.net/",
  "timestamp": 1728902247161,
  "ranks": {
    "hundos": 466,
    "performance": 609,
    "accessibility": 440,
    "cumulative": 467
  },
  "lighthouse": {
    "version": "11.7.1",
    "performance": 0.82,
    "accessibility": 0.95,
    "bestPractices": 1,
    "seo": 1,
    "total": 377
  },
  "firstContentfulPaint": 1712.3455000000001,
  "firstMeaningfulPaint": 1712.3455000000001,
  "speedIndex": 1712.3455000000001,
  "largestContentfulPaint": 2237.1609999999996,
  "totalBlockingTime": 253,
  "cumulativeLayoutShift": 0.21946204348803,
  "timeToInteractive": 4459.0575,
  "maxPotentialFirstInputDelay": 198,
  "timeToFirstByte": 4.567000000000007,
  "weight": {
    "summary": "28 requests • 15.9 MiB",
    "total": 16657391,
    "image": 194065,
    "imageCount": 10,
    "script": 232719,
    "scriptCount": 4,
    "document": 9368,
    "font": 129213,
    "fontCount": 1,
    "stylesheet": 11485,
    "stylesheetCount": 9,
    "thirdParty": 16606783,
    "thirdPartyCount": 5
  },
  "run": {
    "number": 1,
    "total": 3
  },
  "sidequests": {
    "-weight.total": 1004,
    "+weight.total": 21,
    "-weight.document": 459,
    "+weight.document": 553,
    "-weight.script": 685,
    "+weight.script": 276,
    "-weight.image": 406,
    "+weight.image": 508,
    "-weight.font": 518,
    "+weight.font": 226,
    "+weight.fontCount": 18,
    "-timeToFirstByte": 80,
    "-totalBlockingTime": 305,
    "-largestContentfulPaint": 757
  },
  "axe": {
    "passes": 441,
    "violations": 3
  }
}