{
  "url": "https://www.chrisnowicki.io/",
  "requestedUrl": "https://www.chrisnowicki.io/",
  "timestamp": 1693878613478,
  "ranks": {
    "hundos": 242,
    "performance": 118,
    "accessibility": 336,
    "cumulative": 244
  },
  "lighthouse": {
    "version": "9.6.8",
    "performance": 0.99,
    "accessibility": 0.88,
    "bestPractices": 0.92,
    "seo": 1,
    "total": 379
  },
  "firstContentfulPaint": 989.429,
  "firstMeaningfulPaint": 989.429,
  "speedIndex": 989.429,
  "largestContentfulPaint": 2007.429,
  "totalBlockingTime": 10.5,
  "cumulativeLayoutShift": 0,
  "timeToInteractive": 2360.429,
  "maxPotentialFirstInputDelay": 61.000000000000114,
  "timeToFirstByte": 141.758,
  "weight": {
    "summary": "24 requests • 238 KiB",
    "total": 244078,
    "image": 50676,
    "imageCount": 2,
    "script": 144238,
    "scriptCount": 13,
    "document": 19238,
    "font": 11226,
    "fontCount": 1,
    "stylesheet": 6016,
    "stylesheetCount": 2,
    "thirdParty": 0,
    "thirdPartyCount": 2
  },
  "run": {
    "number": 1,
    "total": 3
  },
  "sidequests": {
    "-weight.total": 141,
    "+weight.total": 308,
    "-weight.document": 324,
    "+weight.document": 119,
    "-weight.script": 258,
    "+weight.script": 149,
    "-weight.image": 93,
    "+weight.image": 307,
    "-weight.font": 2,
    "+weight.font": 334,
    "+weight.fontCount": 17,
    "-timeToFirstByte": 329,
    "-totalBlockingTime": 15,
    "-largestContentfulPaint": 270
  },
  "axe": {
    "passes": 238,
    "violations": 14
  }
}